tests/test_mathutils.py
zeynepbayram/__init__.py
zeynepbayram/mathutils.py
zeynepbayram-0.0.1.dist-info/licenses/LICENSE
zeynepbayram-0.0.1.dist-info/METADATA
zeynepbayram-0.0.1.dist-info/WHEEL
zeynepbayram-0.0.1.dist-info/top_level.txt
zeynepbayram-0.0.1.dist-info/RECORD
