Metadata-Version: 2.4
Name: zeynepbayram
Version: 0.0.1
Summary: A simple example package with basic math utilities for Zeynep.
Author-email: Zeynep Bayram <zeeyneepbayram@gmail.com>
License: MIT License
Project-URL: Homepage, https://github.com/Zeynep-Bayram/zeynepbayram
Project-URL: Repository, https://github.com/Zeynep-Bayram/zeynepbayram.git
Keywords: zeynepbayram,math,utilities,example,tutorial
Classifier: Development Status :: 3 - Alpha
Classifier: Intended Audience :: Developers
Classifier: License :: OSI Approved :: MIT License
Classifier: Operating System :: OS Independent
Classifier: Programming Language :: Python :: 3
Classifier: Programming Language :: Python :: 3.7
Classifier: Programming Language :: Python :: 3.8
Classifier: Programming Language :: Python :: 3.9
Classifier: Programming Language :: Python :: 3.10
Classifier: Programming Language :: Python :: 3.11
Classifier: Programming Language :: Python :: 3.12
Classifier: Topic :: Software Development :: Libraries :: Python Modules
Classifier: Topic :: Utilities
Requires-Python: >=3.7
License-File: LICENSE
Dynamic: license-file
